demo/__init__.py
demo/utils_aiohttp.py
rj_utils/__init__.py
rj_utils/engine_event.py
rj_utils/msg_queue_process.py
rj_utils/msg_queue_thread.py
rj_utils/utils_apscheduler.py
rj_utils/utils_cookie.py
rj_utils/utils_datetime.py
rj_utils/utils_dingding_push.py
rj_utils/utils_email.py
rj_utils/utils_file.py
rj_utils/utils_hdf5.py
rj_utils/utils_html.py
rj_utils/utils_json.py
rj_utils/utils_log_handler.py
rj_utils/utils_mysqlconnector.py
rj_utils/utils_num.py
rj_utils/utils_pd2sql.py
rj_utils/utils_port_reforward.py
rj_utils/utils_pymysql.py
rj_utils/utils_queuetask.py
rj_utils/utils_rabbitmq.py
rj_utils/utils_random.py
rj_utils/utils_redis.py
rj_utils/utils_request.py
rj_utils/utils_requests.py
rj_utils/utils_spendtime.py
rj_utils/utils_string.py
rj_utils/utils_sys_signal.py
rj_utils/utils_thread.py
rj_utils/utils_weixin_push.py
rj_utils/utils_zmq.py
RJUtils-1.2.2.dist-info/LICENSE
RJUtils-1.2.2.dist-info/METADATA
RJUtils-1.2.2.dist-info/WHEEL
RJUtils-1.2.2.dist-info/top_level.txt
RJUtils-1.2.2.dist-info/zip-safe
RJUtils-1.2.2.dist-info/RECORD
