Metadata-Version: 2.1
Name: RJUtils
Version: 1.2.2
Summary: RJUtils
Home-page: https://github.com/StarsAaron
Author: Aaron
Author-email: 103514303@qq.com
License: MIT
Platform: UNKNOWN
Classifier: Programming Language :: Python :: 3
Classifier: License :: OSI Approved :: MIT License
Classifier: Operating System :: OS Independent
Requires-Dist: bs4
Requires-Dist: pymysql
Requires-Dist: mysql-connector-python
Requires-Dist: pika
Requires-Dist: apscheduler
Requires-Dist: sqlalchemy
Requires-Dist: requests
Requires-Dist: redis
Requires-Dist: logbook
Requires-Dist: zmq
